[
  {
    "id": "6343b188ac75905b7becc113",
    "index": 0,
    "imge": "https://mb.cision.com/Public/10340/9807907/9e07af0ecad7877f_800x800ar.jpg",
    "name": "Vaunch",
    "about": "Cillum fugiat minim culpa pariatur culpa ullamco est esse elit enim culpa.\r\n",
    "age": 27,
    "time": 60
  },
  {
    "id": "6343b188de37de8304844430",
    "index": 1,
    "imge": "https://bod-blog-assets.prod.cd.beachbodyondemand.com/bod-blog/wp-content/uploads/2017/12/Stability-Ball-Exercises.jpg",
    "name": "Ball Crunch",
    "about": "Commodo amet dolor reprehenderit minim pariatur ipsum id exercitation eiusmod. \r\n",
    "age": 31,
    "time": 120
  },
  {
    "id": "6343b18832a25ba1538d585e",
    "index": 2,
    "imge": "https://www.mensjournal.com/wp-content/uploads/2020/05/DB_Main.jpg?w=1200&quality=86&strip=all",
    "name": "Dumbbell",
    "about": "Velit qui laboris nisi aute eu officia est mollit quis ad quis ad cillum. Pariatur.\r\n",
    "age": 35,
    "time": 180
  },
  {
    "id": "6343b1884545c6b436059962",
    "index": 3,
    "imge": "https://img.livestrong.com/375/clsd/getty/cee709e1db804b7987ade39ddf6a8dd1",
    "name": "bicycle crunch",
    "about": "Laborum nulla ut labore reprehenderit Lorem aliqua amet consequat velit proident tempor. \r\n",
    "age": 24,
    "time": 60
  },
  {
    "id": "6343b188ce4d9edf4d7f619d",
    "index": 4,
    "imge": "https://image.shutterstock.com/image-photo/beautiful-young-model-working-out-260nw-552843544.jpg",
    "name": "Leg Raises",
    "about": "Laboris elit deserunt nulla do duis Lorem enim tempor  occaecat irure reprehenderit deserunt. \r\n",
    "age": 23,
    "time": 30
  },
  {
    "id": "6343b18832d3b9595bc11fff",
    "index": 5,
    "imge": "https://cdn.shopify.com/s/files/1/1876/4703/articles/shutterstock_1481677709_1000x.jpg?v=1642054935",
    "name": "Side Lunges",
    "about": "Nisi eu do enim laboris mollit aute nostrud nisi qui reprehenderit labore qui. Anim ullamco aliqua \r\n",
    "age": 20,
    "time": 180
  }
]
